{"dataResult":{"dataSourceID":"3CA097A2-92D4-4A5B-81DB-31E8A7FAA42E","createdDate":"2025-07-13T18:53:50Z","dataAnalysis":{"classifierAnalysis":{},"objectDetectorAnalysis":{"details":{}},"summary":{"classCount":1},"issues":[{"description":"This object has no materials. Make sure that the asset looks photorealistic to ensure high tracking quality.","severity":"warning"}],"usdzAnalysis":{"objectMeasurements":[{"value":0.008158000186085701,"unit":{"converter":{"constant":0,"coefficient":1},"symbol":"m"}},{"value":0.008158000186085701,"unit":{"converter":{"constant":0,"coefficient":1},"symbol":"m"}},{"value":0.09207600355148315,"unit":{"converter":{"constant":0,"coefficient":1},"symbol":"m"}}]}},"classesCount":1,"dataURL":"file:\/\/\/Users\/debbieyuen\/Downloads\/PinkCrayon.obj.usdz"},"pathType":0,"title":"PinkCrayon.obj.usdz","id":"3CA097A2-92D4-4A5B-81DB-31E8A7FAA42E","dataPathRelativeToProjectURL":"..\/..\/..\/..\/Downloads\/PinkCrayon.obj.usdz\/","experimentIDs":[],"version":"1.0","createdDate":"2025-07-13T18:53:50Z","activityEntities":["dataSourceCreated",[{"event":"dataSourceCreated","title":"Data Source Created","subtitle":"PinkCrayon.obj.usdz","createdDate":"2025-07-13T18:53:50Z","id":"DE54BA77-3D5A-42FE-B0B1-18CD81E47A4A"}]],"modifiedDate":"2025-07-13T21:33:03Z","preferredFilename":"PinkCrayon.obj.usdz","dataURL":"file:\/\/\/Users\/debbieyuen\/Downloads\/PinkCrayon.obj.usdz"}